gapTrick/__init__.py
gapTrick/__main__.py
gapTrick/version.py
gapTrick-1.0.25.dist-info/LICENSE
gapTrick-1.0.25.dist-info/METADATA
gapTrick-1.0.25.dist-info/WHEEL
gapTrick-1.0.25.dist-info/entry_points.txt
gapTrick-1.0.25.dist-info/top_level.txt
gapTrick-1.0.25.dist-info/RECORD
