Metadata-Version: 2.1
Name: gapTrick
Version: 1.0.25
Summary: rebuilds and completes models of protein complexes using AlphaFold2
Home-page: https://github.com/gchojnowski/gapTrick
Author: Grzegorz Chojnowski
Author-email: gchojnowski@embl-hamburg.de
License: BSD
License-File: LICENSE
Requires-Dist: af2plots
Requires-Dist: matplotlib
